ksdisc/__init__.py
ksdisc/ksdisc.py
ksdisc-0.0.9.dist-info/LICENSE
ksdisc-0.0.9.dist-info/METADATA
ksdisc-0.0.9.dist-info/WHEEL
ksdisc-0.0.9.dist-info/top_level.txt
ksdisc-0.0.9.dist-info/RECORD
