Metadata-Version: 2.1
Name: ksdisc
Version: 0.0.9
Summary: Discrete Kolmogorov–Smirnov test
Home-page: https://github.com/ViktorWase/ks-disc
Author: Viktor Wase
Author-email: viktorwase@gmail.com
License: UNKNOWN
Platform: UNKNOWN
Classifier: Programming Language :: Python :: 3
Classifier: License :: OSI Approved :: MIT License
Classifier: Operating System :: OS Independent
Requires-Python: >=3.0
